mojang_python/__init__.py
mojang_python/account.py
mojang_python/info.py
mojang_python/optifine.py
mojang_python-1.2.0.dist-info/LICENSE
mojang_python-1.2.0.dist-info/METADATA
mojang_python-1.2.0.dist-info/WHEEL
mojang_python-1.2.0.dist-info/top_level.txt
mojang_python-1.2.0.dist-info/RECORD
