Metadata-Version: 2.1
Name: mojang-python
Version: 1.2.0
Summary: Easy Mojang API Wrapper
Home-page: https://github.com/Hades1232/mojang_python
Author: Hades_
License: Apache
Platform: UNKNOWN
Requires-Python: >=3.10
License-File: LICENSE
Requires-Dist: requests
Requires-Dist: typing
